docsai/__init__.py
docsai/__main__.py
docsai/_about.py
docsai/_cli.py
docsai/generation.py
docsai-0.5.2.dist-info/LICENSE
docsai-0.5.2.dist-info/METADATA
docsai-0.5.2.dist-info/WHEEL
docsai-0.5.2.dist-info/entry_points.txt
docsai-0.5.2.dist-info/top_level.txt
docsai-0.5.2.dist-info/RECORD
