Metadata-Version: 2.1
Name: docsai
Version: 0.5.2
Summary: Generate markdown API documentation for Google-style Python docstring.
Home-page: https://github.com/khulnasoft/docsai
Author: KhulnaSoft DevOps
Author-email: info@khulnasoft.com
License: MIT
Project-URL: Changelog, https://github.com/khulnasoft/docsai/releases
Project-URL: Issue Tracker, https://github.com/khulnasoft/docsai/issues
Project-URL: Documentation, https://github.com/khulnasoft/docsai#documentation
Project-URL: Source, https://github.com/khulnasoft/docsai
Classifier: Development Status :: 4 - Beta
Classifier: Intended Audience :: Developers
Classifier: Intended Audience :: Science/Research
Classifier: License :: OSI Approved :: MIT License
Classifier: Natural Language :: English
Classifier: Operating System :: OS Independent
Classifier: Programming Language :: Python :: 3 :: Only
Classifier: Programming Language :: Python :: 3
Classifier: Programming Language :: Python :: 3.6
Classifier: Programming Language :: Python :: 3.7
Classifier: Programming Language :: Python :: 3.8
Classifier: Programming Language :: Python :: 3.9
Classifier: Programming Language :: Python :: Implementation :: PyPy
Classifier: Programming Language :: Python :: Implementation :: CPython
Classifier: Topic :: Software Development :: Libraries
Classifier: Topic :: Software Development :: Libraries :: Python Modules
Classifier: Topic :: Documentation
Classifier: Topic :: Documentation :: Sphinx
Classifier: Topic :: Text Processing :: Markup :: Markdown
Classifier: Topic :: Utilities
Requires-Python: >=3.6
License-File: LICENSE
Requires-Dist: typer
Provides-Extra: dev
Requires-Dist: setuptools ; extra == 'dev'
Requires-Dist: wheel ; extra == 'dev'
Requires-Dist: twine ; extra == 'dev'
Requires-Dist: flake8 ; extra == 'dev'
Requires-Dist: pytest ; extra == 'dev'
Requires-Dist: pytest-mock ; extra == 'dev'
Requires-Dist: pytest-cov ; extra == 'dev'
Requires-Dist: mypy ; extra == 'dev'
Requires-Dist: black ; extra == 'dev'
Requires-Dist: pydocstyle ; extra == 'dev'
Requires-Dist: isort ; extra == 'dev'
Requires-Dist: ml-buildkit ; extra == 'dev'
